Metadata-Version: 2.1
Name: embarc-cli
Version: 1.1.1
Summary: This is a command line tool for embarc open source platform
Home-page: https://github.com/foss-for-synopsys-dwc-arc-processors/embarc_tools
Author: Jingru Wang
Author-email: jingru@synopsys.com
License: UNKNOWN
Download-URL: https://github.com/foss-for-synopsys-dwc-arc-processors/embarc_tools.git
Keywords: embARC
Platform: UNKNOWN
Classifier: Programming Language :: Python :: 2
Classifier: Programming Language :: Python :: 3
Classifier: Operating System :: OS Independent
Requires-Python: >=2.7.10,!=3.0.*,!=3.1.*,<4
Requires-Dist: PyYAML
Requires-Dist: colorama
Requires-Dist: Jinja2
Requires-Dist: beautifulsoup4
Requires-Dist: GitPython
Requires-Dist: pyelftools
Requires-Dist: psutil
Requires-Dist: pexpect
